[
  {
    "number":1,
    "date":"2018-08-21",
    "account":"서이",
    "brand":"",
    "shippingType":"직배송",
    "sale":"없음",
    "totalSales":"55,490원",
    "accountCode":"02012012",
    "customerSector":"선택",
    "shipping":"",
    "fax":"",
    "email":"",
    "accoutPhone":"01065567650",
    "accountId":"01065567650",
    "accountPw":"1234",
    "manager":"",
    "managerPhone":"",
    "shippingManager":"박정철",
    "shippingPhone":"01068997774",
    "salesPerson":"",
    "salesPhone":"",
    "product":[13001,13002,13003]
  },
  {
    "number":2,
    "date":"2018-08-20",
    "account":"서울식품",
    "brand":"",
    "shippingType":"직배송",
    "sale":"없음",
    "totalSales":"0원",
    "accountCode":"S0010100010",
    "customerSector":"한식",
    "shipping":["21391","인천 부평구 시장로71번길 20 (부평동)","마린타워 502호"],
    "fax":"",
    "email":"",
    "accoutPhone":"01065567648",
    "accountId":"01065567648",
    "accountPw":"1111",
    "manager":"문종만",
    "managerPhone":"01065567648",
    "shippingManager":"test",
    "shippingPhone":"01010111010",
    "salesPerson":"test",
    "salesPhone":"01010111010",
    "product":[13004,13005,13006]
  },
  {
    "number":3,
    "date":"2018-08-16",
    "account":"대전점",
    "brand":"",
    "shippingType":"택배배송",
    "sale":"10%할증(10%)",
    "totalSales":"0원",
    "accountCode":"1025",
    "customerSector":"선택",
    "shipping":["31163","충남 천안시 서북구 검은들1길 7 (불당동, 포인트프라자빌딩)"],
    "fax":"",
    "email":"",
    "accoutPhone":"01035852864",
    "accountId":"01035852864",
    "accountPw":"2222",
    "manager":"",
    "managerPhone":"",
    "shippingManager":"test1",
    "shippingPhone":"01012345678",
    "salesPerson":"",
    "salesPhone":"",
    "product":[13007,13008,13009]
  },
  {
    "number":4,
    "date":"2018-07-02",
    "account":"파스타앤피자",
    "brand":"토라니",
    "shippingType":"직배송",
    "sale":"없음",
    "totalSales":"182,490원",
    "accountCode":"",
    "customerSector":"한식",
    "shipping":"",
    "fax":"",
    "email":"",
    "accoutPhone":"01055553333",
    "accountId":"01055553333",
    "accountPw":"3333",
    "manager":"",
    "managerPhone":"",
    "shippingManager":"코모리",
    "shippingPhone":"01000000009",
    "salesPerson":"",
    "salesPhone":"",
    "product":[13010,13011,13012]
  },
  {
    "number":5,
    "date":"2018-06-27",
    "account":"골드윙",
    "brand":"",
    "shippingType":"직배송",
    "sale":"없음",
    "totalSales":"0원",
    "accountCode":"",
    "customerSector":"선택",
    "shipping":"",
    "fax":"",
    "email":"",
    "accoutPhone":"1231231234",
    "accountId":"1231231234",
    "accountPw":"4444",
    "manager":"",
    "managerPhone":"",
    "shippingManager":"오미란",
    "shippingPhone":"01046378871",
    "salesPerson":"",
    "salesPhone":"",
    "product":[13013,13014,13015]
  },
  {
    "number":6,
    "date":"2018-06-18",
    "account":"골드윙",
    "brand":"",
    "shippingType":"직배송",
    "sale":"없음",
    "totalSales":"3,000원",
    "accountCode":"",
    "customerSector":"닭/오리",
    "shipping":["48244","부산 수영구 망미번영로 8 (광안동, 평화)"],
    "fax":"",
    "email":"",
    "accoutPhone":"11111111111",
    "accountId":"11111111111",
    "accountPw":"5555",
    "manager":"",
    "managerPhone":"",
    "shippingManager":"오미란",
    "shippingPhone":"01046378871",
    "salesPerson":"",
    "salesPhone":"",
    "product":[13016,13017,13018]
  },
  {
    "number":7,
    "date":"2018-06-18",
    "account":"키위빠",
    "brand":"",
    "shippingType":"직배송",
    "sale":"없음",
    "totalSales":"0원",
    "accountCode":"",
    "customerSector":"유흥주점",
    "shipping":"",
    "fax":"",
    "email":"",
    "accoutPhone":"01020241117",
    "accountId":"01020241117",
    "accountPw":"6666",
    "manager":"",
    "managerPhone":"",
    "shippingManager":"test",
    "shippingPhone":"01010111010",
    "salesPerson":"",
    "salesPhone":"",
    "product":[13019,13020]
  },
  {
    "number":8,
    "date":"2018-06-12",
    "account":"앤아버",
    "brand":"토라니",
    "shippingType":"전체",
    "sale":"없음",
    "totalSales":"1,005,771원",
    "accountCode":"",
    "customerSector":"중식",
    "shipping":["13536","경기 성남시 분당구 판교역로2번길 2 (백현동)","1층 앤아버"],
    "fax":"",
    "email":"",
    "accoutPhone":"026667777",
    "accountId":"026667777",
    "accountPw":"7777",
    "manager":"",
    "managerPhone":"",
    "shippingManager":"코모리",
    "shippingPhone":"01000000009",
    "salesPerson":"",
    "salesPhone":""
  },
  {
    "number":9,
    "date":"2018-06-11",
    "account":"짬뽕의신",
    "brand":"",
    "shippingType":"직배송",
    "sale":"없음",
    "totalSales":"0원",
    "accountCode":"",
    "customerSector":"중식",
    "shipping":"",
    "fax":"",
    "email":"",
    "accoutPhone":"01012341234",
    "accountId":"01012341234",
    "accountPw":"8888",
    "manager":"",
    "managerPhone":"",
    "shippingManager":"코모리",
    "shippingPhone":"01000000009",
    "salesPerson":"",
    "salesPhone":""
  }
]
