[
    {
      "number":1,
      "account":"파스타앤피자",
      "preDeposit":"182,490원",
      "salesAmount":"0원",
      "chargeAmount":"0원",
      "updateAmount":"0원",
      "depositBalance":"182,490원",
      "manager":"코모리",
      "finalDate":"2018-07-13",
      "detail":[
  
      ]
    },
    {
      "number":2,
      "account":"키위빠",
      "preDeposit":"0원",
      "salesAmount":"0원",
      "chargeAmount":"0원",
      "updateAmount":"0원",
      "depositBalance":"0원",
      "manager":"코모리",
      "finalDate":"",
      "detail":[
  
      ]
    },
    {
      "number":3,
      "account":"짬뽕의신",
      "preDeposit":"0원",
      "salesAmount":"0원",
      "chargeAmount":"0원",
      "updateAmount":"0원",
      "depositBalance":"0원",
      "manager":"코모리",
      "finalDate":"",
      "detail":[
  
      ]
    },
    {
      "number":4,
      "account":"앤아버",
      "preDeposit":"328,851원",
      "salesAmount":"676,920원",
      "chargeAmount":"0원",
      "updateAmount":"0원",
      "depositBalance":"1,005,771원",
      "manager":"코모리",
      "finalDate":"2018-08-08",
      "detail":[
        {
          "number":1,
          "date":"2018-08-08 10:37:07",
          "division":"매출",
          "transactionMethod":"외상거래",
          "transactionAmount":"249,270원",
          "totalBalance":"578,121원",
          "remarks":"MRQfu05180801 주문 완료"
        },
        {
          "number":2,
          "date":"2018-08-05 17:25:03",
          "division":"매출",
          "transactionMethod":"외상거래",
          "transactionAmount":"292,170원",
          "totalBalance":"870,291원",
          "remarks":"MRQfu05180802 주문 완료"
        },
        {
          "number":3,
          "date":"2018-08-08 10:37:07",
          "division":"매출",
          "transactionMethod":"외상거래",
          "transactionAmount":"135,480원",
          "totalBalance":"1,005,771원",
          "remarks":"MRQfu08180801 주문 완료"
        }
      ]
    },
    {
      "number":5,
      "account":"서이",
      "preDeposit":"0원",
      "salesAmount":"55,490원",
      "chargeAmount":"0원",
      "updateAmount":"0원",
      "depositBalance":"55,490원",
      "manager":"박정철",
      "finalDate":"2018-08-21"
    },
    {
      "number":6,
      "account":"서울식품",
      "preDeposit":"0원",
      "salesAmount":"0원",
      "chargeAmount":"0원",
      "updateAmount":"0원",
      "depositBalance":"0원",
      "manager":"박정철",
      "finalDate":"2018-08-20"
    },
    {
      "number":7,
      "account":"테스트",
      "preDeposit":"0원",
      "salesAmount":"0원",
      "chargeAmount":"0원",
      "updateAmount":"0원",
      "depositBalance":"0원",
      "manager":"코모리",
      "finalDate":""
    },
    {
      "number":8,
      "account":"대전점",
      "preDeposit":"0원",
      "salesAmount":"0원",
      "chargeAmount":"0원",
      "updateAmount":"0원",
      "depositBalance":"0원",
      "manager":"코모리",
      "finalDate":""
    },
    {
      "number":9,
      "account":"골드윙",
      "preDeposit":"3,000원",
      "salesAmount":"0원",
      "chargeAmount":"0원",
      "updateAmount":"0원",
      "depositBalance":"3,000원",
      "manager":"오미란",
      "finalDate":"2018-06-27"
    },
    {
      "number":10,
      "account":"골드윙",
      "preDeposit":"0원",
      "salesAmount":"0원",
      "chargeAmount":"0원",
      "updateAmount":"0원",
      "depositBalance":"3,000원",
      "manager":"오미란",
      "finalDate":""
    }
  ]